rfc_generator/__init__.py
rfc_generator/src/__init__.py
rfc_generator/src/homoclave.py
rfc_generator/src/rfc_pf.py
rfc_generator/src/rfc_pm.py
rfc_generator/src/verification_digit.py
rfc_generator/test/__init__.py
rfc_generator/test/test_rfc_generator.py
rfc_generator-0.0.14.dist-info/LICENCE
rfc_generator-0.0.14.dist-info/METADATA
rfc_generator-0.0.14.dist-info/WHEEL
rfc_generator-0.0.14.dist-info/top_level.txt
rfc_generator-0.0.14.dist-info/RECORD
