Metadata-Version: 2.1
Name: rfc-generator
Version: 0.0.14
Summary: Generate RFC for PF and PM given input information
Home-page: https://github.com/dimitrj89/rfc_generator
Author: Dimitrj Bonansea
Author-email: dimitrj22@gmail.com
License: MIT
Platform: UNKNOWN
Classifier: License :: OSI Approved :: MIT License
Classifier: Programming Language :: Python :: 3.10
Classifier: Operating System :: OS Independent
Requires-Python: >=3.7
License-File: LICENCE
Requires-Dist: Unidecode (>=1.3.6)
Requires-Dist: num2words (>=0.5.12)
Provides-Extra: dev
Requires-Dist: pytest (>=7.0) ; extra == 'dev'
Requires-Dist: twine (>=4.0.2) ; extra == 'dev'
